h5sparse/__init__.py
h5sparse/h5sparse.py
h5sparse_tensor-0.2.3.dist-info/LICENSE
h5sparse_tensor-0.2.3.dist-info/METADATA
h5sparse_tensor-0.2.3.dist-info/WHEEL
h5sparse_tensor-0.2.3.dist-info/top_level.txt
h5sparse_tensor-0.2.3.dist-info/RECORD
