Metadata-Version: 2.1
Name: h5sparse-tensor
Version: 0.2.3
Summary: Scipy sparse matrices in HDF5. Sparse COO tensors in HDF5
Author: Appier Inc., Tom Vander Aa
License: MIT
Project-URL: Homepage, https://github.com/tvandera/h5sparse
Classifier: Development Status :: 3 - Alpha
Classifier: Intended Audience :: Developers
Classifier: Intended Audience :: Information Technology
Classifier: Intended Audience :: Science/Research
Classifier: License :: OSI Approved :: MIT License
Classifier: Programming Language :: Python :: 3.6
Classifier: Programming Language :: Python :: 3.7
Classifier: Programming Language :: Python :: 3.8
Classifier: Programming Language :: Python :: 3.9
Classifier: Programming Language :: Python :: 3.10
Classifier: Programming Language :: Python :: 3.11
Classifier: Topic :: Database
Classifier: Topic :: Scientific/Engineering
Classifier: Topic :: Software Development :: Libraries :: Python Modules
Requires-Python: >=3.6
License-File: LICENSE
Requires-Dist: h5py
Requires-Dist: numpy
Requires-Dist: scipy
Requires-Dist: six
